rag_module/__init__.py
rag_module/chunker.py
rag_module/document.py
rag_module/embeddings.py
rag_module/loaders.py
rag_module/py.typed
rag_module/rag.py
rag_module/vector_store.py
rag_module-1.0.0.dist-info/METADATA
rag_module-1.0.0.dist-info/WHEEL
rag_module-1.0.0.dist-info/RECORD
