Metadata-Version: 2.4
Name: rag-module
Version: 1.0.0
Summary: A simple RAG module with in-memory vector store and OpenAI integration
Project-URL: Homepage, https://github.com/yourusername/rag-module
Project-URL: Repository, https://github.com/yourusername/rag-module
Author-email: Your Name <your.email@example.com>
License-Expression: MIT
Keywords: augmented,generation,openai,rag,retrieval,vector-store
Classifier: Development Status :: 3 - Alpha
Classifier: Intended Audience :: Developers
Classifier: License :: OSI Approved :: MIT License
Classifier: Programming Language :: Python :: 3
Classifier: Programming Language :: Python :: 3.12
Classifier: Programming Language :: Python :: 3.13
Classifier: Topic :: Scientific/Engineering :: Artificial Intelligence
Requires-Python: >=3.12
Requires-Dist: numpy>=1.26.0
Requires-Dist: openai>=1.0.0
Provides-Extra: dev
Requires-Dist: mypy>=1.8.0; extra == 'dev'
Requires-Dist: pytest-asyncio>=0.23.0; extra == 'dev'
Requires-Dist: pytest>=8.0.0; extra == 'dev'
Requires-Dist: python-dotenv>=1.0.0; extra == 'dev'
Requires-Dist: ruff>=0.1.0; extra == 'dev'
Provides-Extra: examples
Requires-Dist: python-dotenv>=1.0.0; extra == 'examples'
